auto_code_generation_execution.py
auto_code_generation_execution-1.0.4.dist-info/METADATA
auto_code_generation_execution-1.0.4.dist-info/WHEEL
auto_code_generation_execution-1.0.4.dist-info/entry_points.txt
auto_code_generation_execution-1.0.4.dist-info/top_level.txt
auto_code_generation_execution-1.0.4.dist-info/RECORD
