Metadata-Version: 2.1
Name: auto-code-generation-execution
Version: 1.0.4
